l0n0ludp/ChaCha20.py
l0n0ludp/ID生成.py
l0n0ludp/SOCKS5服务器.py
l0n0ludp/UDP心跳.py
l0n0ludp/UDP消息.py
l0n0ludp/__init__.py
l0n0ludp/本地TCP服务器.py
l0n0ludp/本地UDP协议.py
l0n0ludp/远端UDP协议.py
l0n0ludp/远端UDP服务器.py
l0n0ludp/通用.py
l0n0ludp-0.1.2.dist-info/METADATA
l0n0ludp-0.1.2.dist-info/WHEEL
l0n0ludp-0.1.2.dist-info/entry_points.txt
l0n0ludp-0.1.2.dist-info/top_level.txt
l0n0ludp-0.1.2.dist-info/RECORD
