Metadata-Version: 2.4
Name: l0n0ludp
Version: 0.1.2
Summary: Add your description here
Requires-Python: >=3.10
Requires-Dist: pymonocypher
Requires-Dist: uvloop
